setup.py
Database_by_ike_welborn.egg-info/PKG-INFO
Database_by_ike_welborn.egg-info/SOURCES.txt
Database_by_ike_welborn.egg-info/dependency_links.txt
Database_by_ike_welborn.egg-info/top_level.txt
data/__init__.py
data/database.py