Metadata-Version: 1.1
Name: Database-by-ike-welborn
Version: 1.0.1
Summary: a Python for making data programming esier
Home-page: UNKNOWN
Author: Ike Welborn
Author-email: ike.welborn@gmail.com
License: UNKNOWN
Platform: UNKNOWN
Requires: random
